aqipy/__init__.py
aqipy/aqhi_ca.py
aqipy/aqhi_hk.py
aqipy/aqi_au.py
aqipy/aqi_cn.py
aqipy/aqi_in.py
aqipy/aqi_us.py
aqipy/cai_kr.py
aqipy/caqi_eu.py
aqipy/daqi_uk.py
aqipy/psi_sg.py
aqipy/utils.py
aqipy_atmotech-0.1.5.dist-info/LICENSE
aqipy_atmotech-0.1.5.dist-info/METADATA
aqipy_atmotech-0.1.5.dist-info/WHEEL
aqipy_atmotech-0.1.5.dist-info/top_level.txt
aqipy_atmotech-0.1.5.dist-info/RECORD
