Metadata-Version: 2.1
Name: aqipy-atmotech
Version: 0.1.5
Summary: AQI calculation library
Home-page: UNKNOWN
Author: Atmotech Inc.
Author-email: info@atmotube.com
License: Apache-2.0
Platform: UNKNOWN
Classifier: Programming Language :: Python :: 3
Classifier: License :: OSI Approved :: Apache Software License
Classifier: Operating System :: OS Independent
Requires-Python: >=3.6
